{
  "main": {
    "name":"Kevin Baer ",
    "description":"I am a junior web developer exporing the different programming languages that programming has to offer",
    "image":"profile.jpg",
    "bio":"I have been interested in programming and technologies for a long time and enjoy sucess in programming (even if I did struggle for a few hours).",
    "contactmessage":"If you have any question or concerns pleace reach out to me.",
    "email": "kevinbare@my.cwi.edu",
    "phone": "555-555-5555",
    "address":{
      "street":"3835 Wild Wood LN",
      "city":"New Plymouth",
      "state":"Idaho",
      "zip": "83655"
    },
    "website": "http://www.timbakerdev.com",
    "linkedinprofile":"https://www.linkedin.com/in/kevin-baer-13a34b256/",
    "social":[
      {
        "name":"linkedin",
        "url":"https://www.linkedin.com/in/kevin-baer-13a34b256/",
        "className":"fa fa-linkedin"
      },
      {
        "name":"github",
        "url":"https://github.com/kevinbaer",
        "className":"fa fa-github"
      }
    ]
  },
  "resume":{
    "skillmessage":"Here you can create a short write-up of your skills to show off to employers",
    "education":[
      {
        "school":"College of Western Idaho",
        "degree":"Software Development",
        "graduated":"Currently attending.",
        "description":"Learning programming even if it is hard and difficult to understand at times."
      }
    ],
    "work":[
      {
        "company":"None as of yet",
        "title":"Unsure",
        "years":"Future"
      }
    ],
    "skills":[
      {
        "name":"HTML",
        "level":"90%"
      },
      {
        "name":"CSS",
        "level":"85%"
      },
      {
        "name":"JavaScript",
        "level":"40%"
      },
      {
        "name":"C#",
        "level":"40%"
      },
      {
        "name":"C++",
        "level":"45%"
      }
    ]
  },
  "portfolio":{
    "projects": [
      {
        "title":"Swag Pets",
        "category":"Project Website for School",
        "image":"swagforpets.png",
        "url":"https://u8dl3i.csb.app/"
      },
      {
        "title":"First Portfolio",
        "category":"First revision my portfolio website",
        "image":"firstportfolio.png",
        "url":"kevinbaer.github.io/Portfolio Website/Home.html"
      },
      {
        "title":"Second Portfolio",
        "category":"Second revision my portfolio website",
        "image":"secondportfolio.png",
        "url":"https://gu6s9c.csb.app/"
      },
      {
        "title":"Mountains",
        "category":"Simple placeholder website",
        "image":"mountains.png",
        "url":"https://si5bbj.csb.app/"
      }
    ]
  }
}
